rtl/control_unit.v
module control_unit(

    input [6:0] opcode,
    input [2:0] funct3,
    input [6:0] funct7,

    output reg reg_write,
    output reg alu_src,
    output reg mem_read,
    output reg mem_write,
    output reg mem_to_reg,
    output reg branch,
    output reg [3:0] alu_control

);

always @(*) begin

    // Default values
    reg_write   = 0;
    alu_src     = 0;
    mem_read    = 0;
    mem_write   = 0;
    mem_to_reg  = 0;
    branch      = 0;
    alu_control = 4'b0000;

    case(opcode)

        //=========================
        // R-Type Instructions
        //=========================
        7'b0110011: begin

            reg_write  = 1;
            alu_src    = 0;
            mem_to_reg = 0;

            case(funct3)

                // ADD / SUB
                3'b000: begin
                    if(funct7 == 7'b0000000)
                        alu_control = 4'b0000;   // ADD
                    else if(funct7 == 7'b0100000)
                        alu_control = 4'b0001;   // SUB
                end

                // AND
                3'b111:
                    alu_control = 4'b0010;

                // OR
                3'b110:
                    alu_control = 4'b0011;

                default:
                    alu_control = 4'b0000;

            endcase
        end

        //=========================
        // ADDI
        //=========================
        7'b0010011: begin

            reg_write   = 1;
            alu_src     = 1;
            alu_control = 4'b0000;

        end

        //=========================
        // LW
        //=========================
        7'b0000011: begin

            reg_write   = 1;
            alu_src     = 1;
            mem_read    = 1;
            mem_to_reg  = 1;
            alu_control = 4'b0000;

        end

        //=========================
        // SW
        //=========================
        7'b0100011: begin

            reg_write   = 0;
            alu_src     = 1;
            mem_write   = 1;
            alu_control = 4'b0000;

        end

        //=========================
        // BEQ
        //=========================
        7'b1100011: begin

            branch      = 1;
            alu_src     = 0;
            alu_control = 4'b0001;   // SUB

        end

    endcase

end

endmodule

sim/control_unit_tb.v
`timescale 1ns/1ps

module control_unit_tb;

reg [6:0] opcode;
reg [2:0] funct3;
reg [6:0] funct7;

wire reg_write;
wire alu_src;
wire mem_read;
wire mem_write;
wire mem_to_reg;
wire branch;
wire [3:0] alu_control;

control_unit dut(
    .opcode(opcode),
    .funct3(funct3),
    .funct7(funct7),

    .reg_write(reg_write),
    .alu_src(alu_src),
    .mem_read(mem_read),
    .mem_write(mem_write),
    .mem_to_reg(mem_to_reg),
    .branch(branch),
    .alu_control(alu_control)
);

initial begin

    $dumpfile("wave.vcd");
    $dumpvars(0, control_unit_tb);

    //=========================
    // ADD
    //=========================
    opcode = 7'b0110011;
    funct3 = 3'b000;
    funct7 = 7'b0000000;
    #10;

    //=========================
    // SUB
    //=========================
    opcode = 7'b0110011;
    funct3 = 3'b000;
    funct7 = 7'b0100000;
    #10;

    //=========================
    // AND
    //=========================
    opcode = 7'b0110011;
    funct3 = 3'b111;
    funct7 = 7'b0000000;
    #10;

    //=========================
    // OR
    //=========================
    opcode = 7'b0110011;
    funct3 = 3'b110;
    funct7 = 7'b0000000;
    #10;

    //=========================
    // ADDI
    //=========================
    opcode = 7'b0010011;
    funct3 = 3'b000;
    funct7 = 7'b0000000;
    #10;

    //=========================
    // LW
    //=========================
    opcode = 7'b0000011;
    funct3 = 3'b010;
    funct7 = 7'b0000000;
    #10;

    //=========================
    // SW
    //=========================
    opcode = 7'b0100011;
    funct3 = 3'b010;
    funct7 = 7'b0000000;
    #10;

    //=========================
    // BEQ
    //=========================
    opcode = 7'b1100011;
    funct3 = 3'b000;
    funct7 = 7'b0000000;
    #10;

    //=========================
    // Invalid Opcode
    //=========================
    opcode = 7'b1111111;
    funct3 = 3'b000;
    funct7 = 7'b0000000;
    #10;

    $finish;

end

endmodule

wave.vcd
$date
	Thu Jul 23 15:13:38 2026
$end
$version
	Icarus Verilog
$end
$timescale
	1ps
$end
$scope module control_unit_tb $end
$var wire 1 ! reg_write $end
$var wire 1 " mem_write $end
$var wire 1 # mem_to_reg $end
$var wire 1 $ mem_read $end
$var wire 1 % branch $end
$var wire 1 & alu_src $end
$var wire 4 ' alu_control [3:0] $end
$var reg 3 ( funct3 [2:0] $end
$var reg 7 ) funct7 [6:0] $end
$var reg 7 * opcode [6:0] $end
$scope module dut $end
$var wire 3 + funct3 [2:0] $end
$var wire 7 , funct7 [6:0] $end
$var wire 7 - opcode [6:0] $end
$var reg 4 . alu_control [3:0] $end
$var reg 1 & alu_src $end
$var reg 1 % branch $end
$var reg 1 $ mem_read $end
$var reg 1 # mem_to_reg $end
$var reg 1 " mem_write $end
$var reg 1 ! reg_write $end
$upscope $end
$upscope $end
$enddefinitions $end
$comment Show the parameter values. $end
$dumpall
$end
#0
$dumpvars
b0 .
b110011 -
b0 ,
b0 +
b110011 *
b0 )
b0 (
b0 '
0&
0%
0$
0#
0"
1!
$end
#10000
b1 '
b1 .
1!
b100000 )
b100000 ,
#20000
b10 '
b10 .
1!
b0 )
b0 ,
b111 (
b111 +
#30000
b11 '
b11 .
1!
b110 (
b110 +
#40000
1&
b0 '
b0 .
1!
b0 (
b0 +
b10011 *
b10011 -
#50000
1#
1$
1&
1!
b10 (
b10 +
b11 *
b11 -
#60000
1"
0#
0$
1&
0!
b100011 *
b100011 -
#70000
b1 '
b1 .
1%
0"
0&
b0 (
b0 +
b1100011 *
b1100011 -
#80000
b0 '
b0 .
0%
b1111111 *
b1111111 -
